{
    "core": {
        "isLazyAsset": false,
        "uid": "1645812715876798:1490162",
        "type": "Asset.QuaternionAnimationTrackKeyFramed",
        "name": "",
        "keys": [
            [
                0.0,
                [
                    0.0,
                    0.0,
                    0.0,
                    1.0
                ]
            ],
            [
                1.625,
                [
                    0.0,
                    0.0,
                    0.0,
                    1.0
                ]
            ],
            [
                1.6666666269302368,
                [
                    -0.00025185305275954306,
                    -0.0013244906440377235,
                    0.0007220093975774944,
                    0.999998927116394
                ]
            ],
            [
                1.7083333730697632,
                [
                    -0.001911509083583951,
                    -0.014165407977998257,
                    0.007467885501682758,
                    0.9998699426651001
                ]
            ],
            [
                1.75,
                [
                    -0.0006059333682060242,
                    -0.044671375304460526,
                    0.02202015183866024,
                    0.998758852481842
                ]
            ],
            [
                1.7916666269302368,
                [
                    0.004084001295268536,
                    -0.07788648456335068,
                    0.037339892238378525,
                    0.9962543845176697
                ]
            ],
            [
                1.8333333730697632,
                [
                    0.007000670302659273,
                    -0.09269308298826218,
                    0.04411563649773598,
                    0.994692325592041
                ]
            ],
            [
                1.875,
                [
                    0.0063196271657943726,
                    -0.09192218631505966,
                    0.04387542977929115,
                    0.9947790503501892
                ]
            ],
            [
                1.9166666269302368,
                [
                    0.00447250297293067,
                    -0.08979520946741104,
                    0.04321162402629852,
                    0.9950124621391296
                ]
            ],
            [
                1.9583333730697632,
                [
                    0.0018084610346704721,
                    -0.08661366999149323,
                    0.04221273958683014,
                    0.9953457117080688
                ]
            ],
            [
                2.0,
                [
                    -0.00126919976901263,
                    -0.08270415663719177,
                    0.04096636921167374,
                    0.995730996131897
                ]
            ],
            [
                2.0416667461395264,
                [
                    -0.004333473276346922,
                    -0.07840769737958908,
                    0.039553768932819366,
                    0.9961270689964294
                ]
            ],
            [
                2.0833332538604736,
                [
                    -0.006978081073611975,
                    -0.07406105846166611,
                    0.03804713860154152,
                    0.9965032339096069
                ]
            ],
            [
                2.125,
                [
                    -0.00887448713183403,
                    -0.06997077167034149,
                    0.03651085123419762,
                    0.9968412518501282
                ]
            ],
            [
                2.1666667461395264,
                [
                    -0.009831322357058525,
                    -0.0663839727640152,
                    0.03500602766871452,
                    0.9971315264701843
                ]
            ],
            [
                2.2083332538604736,
                [
                    -0.009848341345787048,
                    -0.06346090883016586,
                    0.0335969552397728,
                    0.9973701238632202
                ]
            ],
            [
                2.25,
                [
                    -0.009559362195432186,
                    -0.0610710047185421,
                    0.03236933797597885,
                    0.9975626468658447
                ]
            ],
            [
                2.2916667461395264,
                [
                    -0.009328344836831093,
                    -0.05919749289751053,
                    0.03140487149357796,
                    0.9977085590362549
                ]
            ],
            [
                2.3333332538604736,
                [
                    -0.009175434708595276,
                    -0.057974617928266525,
                    0.03077435865998268,
                    0.9978014230728149
                ]
            ],
            [
                2.375,
                [
                    -0.009120257571339607,
                    -0.05753660574555397,
                    0.030548328533768654,
                    0.9978342056274414
                ]
            ],
            [
                2.4166667461395264,
                [
                    -0.009146126918494701,
                    -0.05774175375699997,
                    0.03065420500934124,
                    0.9978188872337341
                ]
            ],
            [
                2.5,
                [
                    -0.00925961509346962,
                    -0.058646176010370255,
                    0.03112071193754673,
                    0.9977506399154663
                ]
            ],
            [
                2.5416667461395264,
                [
                    -0.009285328909754753,
                    -0.058852117508649826,
                    0.031226880848407745,
                    0.9977349638938904
                ]
            ],
            [
                2.5833332538604736,
                [
                    -0.00924932211637497,
                    -0.05856384336948395,
                    0.031078262254595757,
                    0.9977570176124573
                ]
            ],
            [
                2.625,
                [
                    -0.009120257571339607,
                    -0.05753660574555397,
                    0.030548328533768654,
                    0.9978342056274414
                ]
            ],
            [
                2.6666667461395264,
                [
                    -0.00883918534964323,
                    -0.055331338196992874,
                    0.02940879948437214,
                    0.9979957342147827
                ]
            ],
            [
                2.75,
                [
                    -0.008023416623473167,
                    -0.049158282577991486,
                    0.026205509901046753,
                    0.998414933681488
                ]
            ],
            [
                2.7916667461395264,
                [
                    -0.007671014871448278,
                    -0.04687768220901489,
                    0.025006290525197983,
                    0.9985582232475281
                ]
            ],
            [
                2.8333332538604736,
                [
                    -0.007522286847233772,
                    -0.045517705380916595,
                    0.024307072162628174,
                    0.9986395239830017
                ]
            ],
            [
                2.875,
                [
                    -0.007406677585095167,
                    -0.04469284042716026,
                    0.023875979706645012,
                    0.9986879825592041
                ]
            ],
            [
                2.9166667461395264,
                [
                    -0.007347861770540476,
                    -0.04427526891231537,
                    0.02365761063992977,
                    0.9987121820449829
                ]
            ],
            [
                3.125,
                [
                    -0.00733146769925952,
                    -0.04415912553668022,
                    0.023596858605742455,
                    0.9987188577651978
                ]
            ],
            [
                3.1666667461395264,
                [
                    -0.009419869631528854,
                    -0.059935931116342545,
                    0.03178523853421211,
                    0.9976515769958496
                ]
            ],
            [
                3.2083332538604736,
                [
                    -0.01345309428870678,
                    -0.09980321675539017,
                    0.05188942328095436,
                    0.9935622811317444
                ]
            ],
            [
                3.25,
                [
                    -0.01575862057507038,
                    -0.1416175365447998,
                    0.07203812897205353,
                    0.9871710538864136
                ]
            ],
            [
                3.2916667461395264,
                [
                    -0.01615862362086773,
                    -0.16175174713134766,
                    0.08138380944728851,
                    0.9833371639251709
                ]
            ],
            [
                3.3333332538604736,
                [
                    -0.01617407612502575,
                    -0.16394966840744019,
                    0.08238961547613144,
                    0.9828890562057495
                ]
            ],
            [
                4.375,
                [
                    -0.016173752024769783,
                    -0.16389359533786774,
                    0.08236398547887802,
                    0.9829005599021912
                ]
            ],
            [
                4.875,
                [
                    -0.01617054082453251,
                    -0.16336984932422638,
                    0.08212455362081528,
                    0.9830079078674316
                ]
            ],
            [
                5.166666507720947,
                [
                    -0.01616327464580536,
                    -0.16233621537685394,
                    0.08165154606103897,
                    0.9832185506820679
                ]
            ],
            [
                5.375,
                [
                    -0.016151316463947296,
                    -0.16091930866241455,
                    0.0810021236538887,
                    0.983505368232727
                ]
            ],
            [
                5.416666507720947,
                [
                    -0.01598937436938286,
                    -0.1565462052822113,
                    0.07897564023733139,
                    0.9843782186508179
                ]
            ],
            [
                5.458333492279053,
                [
                    -0.011467143893241882,
                    -0.1405661702156067,
                    0.07089290767908096,
                    0.9874633550643921
                ]
            ],
            [
                5.5,
                [
                    0.0037792259827256203,
                    -0.1107519194483757,
                    0.05381110683083534,
                    0.9923830628395081
                ]
            ],
            [
                5.541666507720947,
                [
                    0.029264792799949646,
                    -0.0750049278140068,
                    0.02984408661723137,
                    0.9963067770004272
                ]
            ],
            [
                5.583333492279053,
                [
                    0.05578581243753433,
                    -0.04752238094806671,
                    0.007787321228533983,
                    0.9972807765007019
                ]
            ],
            [
                5.625,
                [
                    0.07247630506753922,
                    -0.03723635897040367,
                    -0.0030269792769104242,
                    0.9966701865196228
                ]
            ],
            [
                5.666666507720947,
                [
                    0.07747457921504974,
                    -0.03857303038239479,
                    -0.003776435274630785,
                    0.9962407350540161
                ]
            ],
            [
                5.708333492279053,
                [
                    0.07790272682905197,
                    -0.03878919780254364,
                    -0.0037805959582328796,
                    0.9961990118026733
                ]
            ],
            [
                5.75,
                [
                    0.07182791829109192,
                    -0.03572487831115723,
                    -0.0037041001487523317,
                    0.9967702627182007
                ]
            ],
            [
                5.791666507720947,
                [
                    0.033240363001823425,
                    -0.016409792006015778,
                    -0.0023498244117945433,
                    0.9993098974227905
                ]
            ],
            [
                5.833333492279053,
                [
                    0.0011553183430805802,
                    -0.0005664954660460353,
                    -9.980337927117944e-05,
                    0.9999991655349731
                ]
            ],
            [
                5.875,
                [
                    0.0,
                    0.0,
                    0.0,
                    1.0
                ]
            ],
            [
                6.166666507720947,
                [
                    0.0001643811265239492,
                    -8.058462117332965e-05,
                    -1.4279497918323614e-05,
                    1.0
                ]
            ],
            [
                6.208333492279053,
                [
                    0.001440920983441174,
                    -0.0007065812824293971,
                    -0.00012427516048774123,
                    0.9999988079071045
                ]
            ],
            [
                6.25,
                [
                    0.0038989693857729435,
                    -0.0019129564752802253,
                    -0.00033160828752443194,
                    0.9999905228614807
                ]
            ],
            [
                6.291666507720947,
                [
                    0.005370910745114088,
                    -0.0026359811890870333,
                    -0.00045294585288502276,
                    0.9999819993972778
                ]
            ],
            [
                6.333333492279053,
                [
                    0.002699014963582158,
                    -0.0013238743413239717,
                    -0.000231129044550471,
                    0.9999954700469971
                ]
            ],
            [
                6.375,
                [
                    0.0003107754164375365,
                    -0.0001523564278613776,
                    -2.6974374122801237e-05,
                    0.9999999403953552
                ]
            ],
            [
                6.416666507720947,
                [
                    1.7258131510418712e-20,
                    -8.460152889186614e-21,
                    -1.5005634893854247e-21,
                    1.0
                ]
            ],
            [
                6.708333492279053,
                [
                    2.45029690981724e-15,
                    -1.2011656699191802e-15,
                    -2.1304895620651303e-16,
                    1.0
                ]
            ],
            [
                6.75,
                [
                    0.0003522812621667981,
                    -0.00017270607349928468,
                    -3.056984132854268e-05,
                    0.9999999403953552
                ]
            ],
            [
                6.791666507720947,
                [
                    0.0017768021207302809,
                    -0.0008713506977073848,
                    -0.00015295342018362135,
                    0.9999980330467224
                ]
            ],
            [
                6.833333492279053,
                [
                    0.004355337005108595,
                    -0.002137077273800969,
                    -0.0003694543556775898,
                    0.9999882578849792
                ]
            ],
            [
                6.875,
                [
                    0.0075133731588721275,
                    -0.0036891894415020943,
                    -0.0006257802015170455,
                    0.9999647736549377
                ]
            ],
            [
                6.916666507720947,
                [
                    0.010228022001683712,
                    -0.0050250631757080555,
                    -0.0008383361273445189,
                    0.999934732913971
                ]
            ],
            [
                6.958333492279053,
                [
                    0.011359849013388157,
                    -0.005582489538937807,
                    -0.0009248304995708168,
                    0.9999194741249084
                ]
            ],
            [
                7.208333492279053,
                [
                    0.010979018174111843,
                    -0.0053948997519910336,
                    -0.0008958671824075282,
                    0.9999247789382935
                ]
            ],
            [
                7.541666507720947,
                [
                    0.009495563805103302,
                    -0.004664469975978136,
                    -0.0007816942525096238,
                    0.999943733215332
                ]
            ],
            [
                8.583333015441895,
                [
                    0.0026465223636478186,
                    -0.001298111747018993,
                    -0.00022670150792691857,
                    0.9999956488609314
                ]
            ],
            [
                8.958333015441895,
                [
                    0.001038806396536529,
                    -0.0005093521904200315,
                    -8.979727135738358e-05,
                    0.9999993443489075
                ]
            ],
            [
                9.375,
                [
                    0.00019120157230645418,
                    -9.3733353423886e-05,
                    -1.660684574744664e-05,
                    1.0
                ]
            ],
            [
                11.375,
                [
                    0.0,
                    0.0,
                    0.0,
                    1.0
                ]
            ]
        ]
    }
}
