{
    "core": {
        "isLazyAsset": false,
        "uid": "1646688658581129:684615",
        "type": "Asset.Vec3AnimationTrackKeyFramed",
        "name": "",
        "keys": [
            [
                0.0,
                [
                    2.2644267082214355,
                    1.4210854715202004e-14,
                    8.090399461480047e-09
                ]
            ],
            [
                6.633333206176758,
                [
                    2.2644267082214355,
                    -1.4210854715202004e-14,
                    1.633174306903129e-08
                ]
            ]
        ]
    }
}
