{
    "core": {
        "isLazyAsset": false,
        "uid": "1646688658331097:681748",
        "type": "Asset.Vec3AnimationTrackKeyFramed",
        "name": "",
        "keys": [
            [
                0.0,
                [
                    -7.8558149337768555,
                    -5.684341886080802e-14,
                    -2.842170943040401e-14
                ]
            ],
            [
                6.633333206176758,
                [
                    -7.8558149337768555,
                    -8.526512829121202e-14,
                    -2.4868995751603507e-14
                ]
            ]
        ]
    }
}
