{
    "privateAssets": {
        "1645238215623083:73149": {
            "isLazyAsset": false,
            "uid": "1645238215623083:73149",
            "type": "Asset.RenderMesh",
            "name": "Meshes/Car/Bearing.mesh",
            "provider": {
                "type": "Provider.FileRenderObjectProvider",
                "fileinfo": {
                    "path": "Files/File_1675109166452921_25943.mesh",
                    "location": 0
                },
                "filename": "Files/File_1675109166452921_25943.mesh"
            }
        }
    }
}
