{
    "1645770574370389:5669022": {
        "Compression::IController": {
            "compressed_files": "",
            "infos": {
                "compressedRAM": "1224",
                "compressedSize": "790",
                "extension": "mesh",
                "originalRAM": "1224",
                "originalSize": "790",
                "settings": {
                    "attributeFormat": "",
                    "draco": {
                        "colorBits": "8",
                        "compressLvl": "7",
                        "normalBits": "8",
                        "posBits": "11",
                        "texBits": "10"
                    },
                    "info": {
                        "hasBlendShapes": "false",
                        "vertexAttribs": [
                            {
                                "canBeDisabled": "false",
                                "format": "9",
                                "semantic": "position"
                            },
                            {
                                "canBeDisabled": "true",
                                "format": "9",
                                "semantic": "normal"
                            },
                            {
                                "canBeDisabled": "true",
                                "format": "9",
                                "semantic": "tangent"
                            },
                            {
                                "canBeDisabled": "true",
                                "format": "9",
                                "semantic": "texture0"
                            }
                        ]
                    },
                    "isCompressed": "false",
                    "type": "0"
                }
            },
            "uncompressed_file": "1675109166452946:25963"
        }
    },
    "1675109166452805:25829": {
        "IResourceController": {
            "name": "Cube 1",
            "type": 3,
            "subtype": 0,
            "dependency": 0,
            "hidden": false,
            "uid": "1645770574370389:5669022",
            "fileId": "1675109166452944:25962",
            "publicId": "1675109166453506:26117",
            "expected_hash": "af8d8e4ff3d7350e3363cb2556f6a4a9",
            "additional": {
                "info": {
                    "hasBlendShapes": "false",
                    "vertexAttribs": [
                        {
                            "canBeDisabled": "false",
                            "format": "9",
                            "semantic": "position"
                        },
                        {
                            "canBeDisabled": "true",
                            "format": "9",
                            "semantic": "normal"
                        },
                        {
                            "canBeDisabled": "true",
                            "format": "9",
                            "semantic": "tangent"
                        },
                        {
                            "canBeDisabled": "true",
                            "format": "9",
                            "semantic": "texture0"
                        }
                    ]
                }
            }
        },
        "IResourceManager": {
            "uid": "1645770574370389:5669022",
            "name": "Files/File_1675109166452944_25962.mesh",
            "flags": 1
        }
    },
    "1675109166452944:25962": {
        "IFileManager": {
            "path": "Files/File_1675109166452944_25962.mesh"
        }
    },
    "1675109166452946:25963": {
        "IFileManager": {
            "path": "Files/File_1675109166452946_25963.mesh"
        }
    },
    "1675109166453506:26117": {
        "IResourceController": {
            "public": {
                "path": "Meshes/Road/Cube 1.mesh",
                "hash": "af8d8e4ff3d7350e3363cb2556f6a4a9"
            }
        }
    }
}
