{
    "core": {
        "isLazyAsset": false,
        "uid": "1645812458265872:1067281",
        "type": "Asset.Vec3AnimationTrackKeyFramed",
        "name": "",
        "keys": [
            [
                0.0,
                [
                    18.51051139831543,
                    -3.585482842430928e-15,
                    -6.2559232976022055e-16
                ]
            ],
            [
                0.23333333432674408,
                [
                    18.449323654174805,
                    -5.483470224925107e-15,
                    -6.471925169481525e-16
                ]
            ],
            [
                0.2666666805744171,
                [
                    18.415428161621094,
                    2.443702123048155e-15,
                    5.719771029627139e-16
                ]
            ],
            [
                0.30000001192092896,
                [
                    18.376243591308594,
                    3.2489329355642714e-15,
                    1.4597525467381829e-15
                ]
            ],
            [
                0.36666667461395264,
                [
                    18.284954071044922,
                    3.1531760726354096e-15,
                    1.011404031712852e-15
                ]
            ],
            [
                0.6000000238418579,
                [
                    17.907310485839844,
                    2.75523131192763e-15,
                    2.202365866293374e-16
                ]
            ],
            [
                0.6666666865348816,
                [
                    17.80716323852539,
                    -2.4622288511869745e-15,
                    2.1885002016446171e-16
                ]
            ],
            [
                0.699999988079071,
                [
                    17.76207160949707,
                    1.0352333978597204e-15,
                    8.842642275113039e-16
                ]
            ],
            [
                0.7333333492279053,
                [
                    17.72128677368164,
                    -4.153362105873944e-15,
                    -1.2259320927337282e-16
                ]
            ],
            [
                0.7666666507720947,
                [
                    17.685546875,
                    5.360693116857951e-16,
                    -2.274200877665439e-16
                ]
            ],
            [
                0.8333333134651184,
                [
                    17.632150650024414,
                    -4.614040455995982e-16,
                    -2.3600296674195333e-16
                ]
            ],
            [
                1.0666667222976685,
                [
                    17.684396743774414,
                    1.7609810738252168e-15,
                    1.5202098409858138e-15
                ]
            ],
            [
                1.100000023841858,
                [
                    17.720691680908203,
                    -7.37357162480123e-16,
                    4.0934759765305585e-16
                ]
            ],
            [
                1.1333333253860474,
                [
                    17.762548446655273,
                    -1.2744921051410351e-14,
                    -1.920983268220949e-15
                ]
            ],
            [
                1.2000000476837158,
                [
                    17.859750747680664,
                    -1.460160710739641e-15,
                    4.0787201331937966e-16
                ]
            ],
            [
                1.4333332777023315,
                [
                    18.259641647338867,
                    -3.3173727741859452e-15,
                    -1.8672818028815e-15
                ]
            ],
            [
                1.5,
                [
                    18.363039016723633,
                    -7.203342672237704e-15,
                    -3.199679028472618e-15
                ]
            ],
            [
                1.5333333015441895,
                [
                    18.408676147460938,
                    6.791539817238134e-16,
                    -9.103859162763487e-17
                ]
            ],
            [
                1.5666667222976685,
                [
                    18.449138641357422,
                    -4.8661962351629565e-15,
                    -1.902920714137225e-15
                ]
            ],
            [
                1.6333333253860474,
                [
                    18.511144638061523,
                    4.789126824874656e-15,
                    2.121714406610694e-15
                ]
            ],
            [
                1.899999976158142,
                [
                    18.456161499023438,
                    5.66129462780578e-15,
                    4.637243335399238e-16
                ]
            ],
            [
                1.9333332777023315,
                [
                    18.41937255859375,
                    6.3274360658773995e-15,
                    9.07993061435245e-16
                ]
            ],
            [
                2.0,
                [
                    18.332622528076172,
                    2.5526777821518673e-15,
                    -1.3120073426056938e-15
                ]
            ],
            [
                2.0999999046325684,
                [
                    18.18040657043457,
                    -6.773214682940761e-15,
                    -6.450192951032939e-16
                ]
            ],
            [
                2.2333333492279053,
                [
                    17.9665584564209,
                    -6.329154272210905e-15,
                    -6.436154968118976e-16
                ]
            ],
            [
                2.299999952316284,
                [
                    17.86796760559082,
                    5.374036532755167e-15,
                    5.357976788075225e-16
                ]
            ],
            [
                2.366666555404663,
                [
                    17.782638549804688,
                    -4.000609031199051e-15,
                    4.828586489997208e-16
                ]
            ],
            [
                2.4000000953674316,
                [
                    17.746889114379883,
                    4.603624491843596e-15,
                    1.3712604736396843e-15
                ]
            ],
            [
                2.4666666984558105,
                [
                    17.69341278076172,
                    8.433907055811068e-15,
                    4.835095408801265e-16
                ]
            ],
            [
                2.700000047683716,
                [
                    17.737407684326172,
                    1.3320601064781105e-15,
                    -1.5978524808211688e-16
                ]
            ],
            [
                2.7333333492279053,
                [
                    17.77105140686035,
                    7.036351820752414e-15,
                    -5.5498015603130485e-17
                ]
            ],
            [
                2.7666666507720947,
                [
                    17.809955596923828,
                    -3.4956357283750595e-15,
                    -6.762455352807382e-16
                ]
            ],
            [
                2.8333332538604736,
                [
                    17.900588989257813,
                    5.257445623939165e-16,
                    7.211727980778167e-16
                ]
            ],
            [
                3.066666603088379,
                [
                    18.273523330688477,
                    1.5102552450918852e-16,
                    -1.3217633622130505e-15
                ]
            ],
            [
                3.133333444595337,
                [
                    18.371719360351563,
                    -4.31690950373085e-16,
                    -7.661243071930104e-16
                ]
            ],
            [
                3.200000047683716,
                [
                    18.455881118774414,
                    5.229145194380214e-15,
                    1.3509351769164886e-15
                ]
            ],
            [
                3.2666666507720947,
                [
                    18.520166397094727,
                    -6.539057506869993e-15,
                    -1.2017654751249546e-15
                ]
            ],
            [
                3.3333332538604736,
                [
                    18.55848503112793,
                    4.1860808710440095e-15,
                    2.625878104755788e-16
                ]
            ],
            [
                3.5333333015441895,
                [
                    18.493396759033203,
                    -3.596091083062341e-15,
                    -2.0310329386320005e-16
                ]
            ],
            [
                3.566666603088379,
                [
                    18.458759307861328,
                    -5.9107267725308586e-15,
                    -1.0933577516123762e-15
                ]
            ],
            [
                3.5999999046325684,
                [
                    18.418758392333984,
                    8.605758182347704e-15,
                    1.3487302442756672e-15
                ]
            ],
            [
                3.6666667461395264,
                [
                    18.325624465942383,
                    5.609545149893279e-15,
                    9.558928804815942e-16
                ]
            ],
            [
                3.9000000953674316,
                [
                    17.941965103149414,
                    -2.4766946916184203e-15,
                    -1.4450979238386178e-15
                ]
            ],
            [
                3.9666666984558105,
                [
                    17.840389251708984,
                    -7.69145038441156e-16,
                    -3.362623656508434e-16
                ]
            ],
            [
                4.0,
                [
                    17.794597625732422,
                    -2.5729915380511567e-15,
                    -1.003114861411903e-15
                ]
            ],
            [
                4.0333333015441895,
                [
                    17.753116607666016,
                    -5.0415379844752275e-15,
                    -5.666823000094272e-16
                ]
            ],
            [
                4.066666603088379,
                [
                    17.71668815612793,
                    -7.207736232135113e-15,
                    -7.825316000791222e-16
                ]
            ],
            [
                4.133333206176758,
                [
                    17.66193199157715,
                    -9.89829234337514e-15,
                    -4.580483657603727e-16
                ]
            ],
            [
                4.366666793823242,
                [
                    17.709535598754883,
                    -1.3476433951252215e-15,
                    -7.002362612040585e-16
                ]
            ],
            [
                4.400000095367432,
                [
                    17.745174407958984,
                    -1.2924627985016297e-15,
                    1.87306883785626e-16
                ]
            ],
            [
                4.433333396911621,
                [
                    17.786376953125,
                    2.7982010815836037e-15,
                    1.1876412007294892e-15
                ]
            ],
            [
                4.5,
                [
                    17.882129669189453,
                    -4.235715731203691e-15,
                    -2.5826132499968144e-16
                ]
            ],
            [
                4.733333110809326,
                [
                    18.269886016845703,
                    -5.648841125898774e-15,
                    -1.8672818028815e-15
                ]
            ],
            [
                4.800000190734863,
                [
                    18.368267059326172,
                    -3.0955877848592474e-15,
                    3.53015777375027e-16
                ]
            ],
            [
                4.833333492279053,
                [
                    18.411231994628906,
                    -9.645919723773669e-15,
                    -3.199663146604857e-15
                ]
            ],
            [
                4.866666793823242,
                [
                    18.44894027709961,
                    3.518518746961608e-16,
                    -1.0147421885579812e-15
                ]
            ],
            [
                4.933333396911621,
                [
                    18.50516128540039,
                    3.567881497786984e-15,
                    1.233535986910569e-15
                ]
            ],
            [
                5.166666507720947,
                [
                    18.45978546142578,
                    4.665432909521216e-15,
                    -4.515763458290802e-16
                ]
            ],
            [
                5.199999809265137,
                [
                    18.42525291442871,
                    3.3298466048836857e-15,
                    -8.685407019718631e-16
                ]
            ],
            [
                5.233333110809326,
                [
                    18.385421752929688,
                    -1.8882145281069957e-15,
                    -1.312452987815068e-15
                ]
            ],
            [
                5.300000190734863,
                [
                    18.29282569885254,
                    1.4424547575267108e-15,
                    -1.3120073426056938e-15
                ]
            ],
            [
                5.5333333015441895,
                [
                    17.9105224609375,
                    4.106944700364408e-15,
                    2.2429644201530687e-15
                ]
            ],
            [
                5.599999904632568,
                [
                    17.809051513671875,
                    -2.4530313439292137e-15,
                    9.170846234001501e-17
                ]
            ],
            [
                5.633333206176758,
                [
                    17.763307571411133,
                    -3.223456513851467e-15,
                    -6.275817983950841e-16
                ]
            ],
            [
                5.666666507720947,
                [
                    17.721872329711914,
                    -5.034065565693668e-16,
                    -1.0714513620140118e-15
                ]
            ],
            [
                5.699999809265137,
                [
                    17.685489654541016,
                    -1.7246467485197963e-15,
                    3.898772218714357e-17
                ]
            ],
            [
                5.766666889190674,
                [
                    17.63083267211914,
                    2.2721692691414497e-15,
                    9.275988036697483e-16
                ]
            ],
            [
                6.0,
                [
                    17.671783447265625,
                    -4.27456616787893e-15,
                    -9.369413653197265e-16
                ]
            ],
            [
                6.0333333015441895,
                [
                    17.705156326293945,
                    -1.207057101704689e-15,
                    -5.55098700939251e-16
                ]
            ],
            [
                6.066666603088379,
                [
                    17.743837356567383,
                    2.194257272828868e-15,
                    -1.211344994241927e-16
                ]
            ],
            [
                6.133333206176758,
                [
                    17.83417510986328,
                    5.881946075290815e-16,
                    4.852504053449709e-16
                ]
            ],
            [
                6.400000095367432,
                [
                    18.260404586791992,
                    -9.743669866985657e-15,
                    -1.7695081545052258e-15
                ]
            ],
            [
                6.4666666984558105,
                [
                    18.35369300842285,
                    -1.3475455628198137e-15,
                    -2.1071208494926702e-16
                ]
            ],
            [
                6.5,
                [
                    18.3942928314209,
                    -1.1229911145687731e-14,
                    -2.7568900141965906e-15
                ]
            ],
            [
                6.566666603088379,
                [
                    18.459714889526367,
                    2.2316973996469288e-15,
                    -5.356316603498607e-16
                ]
            ],
            [
                6.633333206176758,
                [
                    18.499189376831055,
                    -1.0801932502494446e-14,
                    -2.1799045112958805e-15
                ]
            ]
        ]
    }
}
