{
    "core": {
        "isLazyAsset": false,
        "uid": "1645812458690026:1070067",
        "type": "Asset.QuaternionAnimationTrackKeyFramed",
        "name": "",
        "keys": [
            [
                0.0,
                [
                    -0.026019329205155373,
                    -0.08625069260597229,
                    -0.014255128800868988,
                    0.9958316087722778
                ]
            ],
            [
                0.03333333507180214,
                [
                    -0.026019329205155373,
                    -0.08625069260597229,
                    -0.014255128800868988,
                    0.9958316087722778
                ]
            ],
            [
                0.06666667014360428,
                [
                    -0.024836674332618713,
                    -0.08639247715473175,
                    -0.015480143949389458,
                    0.9958312511444092
                ]
            ],
            [
                0.10000000149011612,
                [
                    -0.023529009893536568,
                    -0.08657177537679672,
                    -0.016886360943317413,
                    0.9958245754241943
                ]
            ],
            [
                0.13333334028720856,
                [
                    -0.02214249223470688,
                    -0.08676186203956604,
                    -0.018374281004071236,
                    0.9958134889602661
                ]
            ],
            [
                0.1666666716337204,
                [
                    -0.02071519009768963,
                    -0.0869629755616188,
                    -0.019911887124180794,
                    0.9957970976829529
                ]
            ],
            [
                0.20000000298023224,
                [
                    -0.01928478106856346,
                    -0.08717663586139679,
                    -0.021467434242367744,
                    0.9957748055458069
                ]
            ],
            [
                0.23333333432674408,
                [
                    -0.017888562753796577,
                    -0.08740511536598206,
                    -0.023009490221738815,
                    0.9957464337348938
                ]
            ],
            [
                0.2666666805744171,
                [
                    -0.016563402488827705,
                    -0.08765102922916412,
                    -0.0245065800845623,
                    0.9957121014595032
                ]
            ],
            [
                0.30000001192092896,
                [
                    -0.01534572709351778,
                    -0.08791673928499222,
                    -0.025927182286977768,
                    0.9956721067428589
                ]
            ],
            [
                0.3333333432674408,
                [
                    -0.01427155639976263,
                    -0.08820410817861557,
                    -0.027239546179771423,
                    0.9956276416778564
                ]
            ],
            [
                0.36666667461395264,
                [
                    -0.013376622460782528,
                    -0.08851400762796402,
                    -0.028411343693733215,
                    0.9955797791481018
                ]
            ],
            [
                0.4000000059604645,
                [
                    -0.012669024989008904,
                    -0.0888420045375824,
                    -0.029421908780932426,
                    0.9955304861068726
                ]
            ],
            [
                0.4333333373069763,
                [
                    -0.012145554646849632,
                    -0.08917983621358871,
                    -0.03025490790605545,
                    0.9954818487167358
                ]
            ],
            [
                0.46666666865348816,
                [
                    -0.01179459411650896,
                    -0.08951520919799805,
                    -0.030898291617631912,
                    0.9954363107681274
                ]
            ],
            [
                0.5,
                [
                    -0.011598759330809116,
                    -0.08983258903026581,
                    -0.03134222701191902,
                    0.9953960180282593
                ]
            ],
            [
                0.5333333611488342,
                [
                    -0.01155244093388319,
                    -0.09011686593294144,
                    -0.031570762395858765,
                    0.9953636527061462
                ]
            ],
            [
                0.5666666626930237,
                [
                    -0.011647606268525124,
                    -0.09035120904445648,
                    -0.03156879544258118,
                    0.9953413605690002
                ]
            ],
            [
                0.6000000238418579,
                [
                    -0.0118690375238657,
                    -0.09051334112882614,
                    -0.03131747245788574,
                    0.9953319430351257
                ]
            ],
            [
                0.6333333253860474,
                [
                    -0.012197579257190228,
                    -0.0905795469880104,
                    -0.030798068270087242,
                    0.9953381419181824
                ]
            ],
            [
                0.6666666865348816,
                [
                    -0.012611499056220055,
                    -0.09058787673711777,
                    -0.030176879838109016,
                    0.995351254940033
                ]
            ],
            [
                0.699999988079071,
                [
                    -0.013085477985441685,
                    -0.09059056639671326,
                    -0.02966122515499592,
                    0.9953604936599731
                ]
            ],
            [
                0.7333333492279053,
                [
                    -0.013600235804915428,
                    -0.09058893471956253,
                    -0.029192669317126274,
                    0.9953675270080566
                ]
            ],
            [
                0.7666666507720947,
                [
                    -0.014134609140455723,
                    -0.09058073908090591,
                    -0.028690991923213005,
                    0.995375394821167
                ]
            ],
            [
                0.800000011920929,
                [
                    -0.014680733904242516,
                    -0.09056548029184341,
                    -0.028163062408566475,
                    0.9953839778900146
                ]
            ],
            [
                0.8333333134651184,
                [
                    -0.015230837278068066,
                    -0.09054284542798996,
                    -0.02761574275791645,
                    0.9953930974006653
                ]
            ],
            [
                0.8666666746139526,
                [
                    -0.015777379274368286,
                    -0.09051264077425003,
                    -0.027055880054831505,
                    0.9954026937484741
                ]
            ],
            [
                0.8999999761581421,
                [
                    -0.016312936320900917,
                    -0.09047481417655945,
                    -0.02649025432765484,
                    0.9954127073287964
                ]
            ],
            [
                0.9333333373069763,
                [
                    -0.016830239444971085,
                    -0.09042944759130478,
                    -0.02592553198337555,
                    0.9954230785369873
                ]
            ],
            [
                0.9666666388511658,
                [
                    -0.017322184517979622,
                    -0.09037671238183975,
                    -0.025368303060531616,
                    0.9954338073730469
                ]
            ],
            [
                1.0,
                [
                    -0.01778179407119751,
                    -0.09031687676906586,
                    -0.024824954569339752,
                    0.9954448342323303
                ]
            ],
            [
                1.0333333015441895,
                [
                    -0.01820223033428192,
                    -0.09025027602910995,
                    -0.024301793426275253,
                    0.9954562783241272
                ]
            ],
            [
                1.0666667222976685,
                [
                    -0.018576737493276596,
                    -0.0901772677898407,
                    -0.02380489557981491,
                    0.9954679012298584
                ]
            ],
            [
                1.100000023841858,
                [
                    -0.018898649141192436,
                    -0.09009827673435211,
                    -0.0233402531594038,
                    0.9954800009727478
                ]
            ],
            [
                1.1333333253860474,
                [
                    -0.019161373376846313,
                    -0.09001371264457703,
                    -0.02291369065642357,
                    0.9954925179481506
                ]
            ],
            [
                1.1666666269302368,
                [
                    -0.019358284771442413,
                    -0.08992395550012589,
                    -0.02253088355064392,
                    0.9955055713653564
                ]
            ],
            [
                1.2000000476837158,
                [
                    -0.01957380771636963,
                    -0.08982515335083008,
                    -0.022161342203617096,
                    0.9955185651779175
                ]
            ],
            [
                1.2333333492279053,
                [
                    -0.019885461777448654,
                    -0.08971449732780457,
                    -0.021777179092168808,
                    0.9955308437347412
                ]
            ],
            [
                1.2666666507720947,
                [
                    -0.020276153460144997,
                    -0.08959389477968216,
                    -0.021387990564107895,
                    0.9955423474311829
                ]
            ],
            [
                1.2999999523162842,
                [
                    -0.020723039284348488,
                    -0.08946464955806732,
                    -0.021005794405937195,
                    0.9955528974533081
                ]
            ],
            [
                1.3333333730697632,
                [
                    -0.02120986022055149,
                    -0.08932868391275406,
                    -0.020639600232243538,
                    0.9955624341964722
                ]
            ],
            [
                1.3666666746139526,
                [
                    -0.02170293778181076,
                    -0.0891861617565155,
                    -0.02030600979924202,
                    0.9955714344978333
                ]
            ],
            [
                1.399999976158142,
                [
                    -0.022172503173351288,
                    -0.08903742581605911,
                    -0.020019691437482834,
                    0.9955801963806152
                ]
            ],
            [
                1.4333332777023315,
                [
                    -0.022607631981372833,
                    -0.08888442814350128,
                    -0.019786909222602844,
                    0.9955888390541077
                ]
            ],
            [
                1.5,
                [
                    -0.023340411484241486,
                    -0.08857228606939316,
                    -0.019503606483340263,
                    0.9956052303314209
                ]
            ],
            [
                1.5333333015441895,
                [
                    -0.02362600527703762,
                    -0.08841632306575775,
                    -0.01946353353559971,
                    0.995613157749176
                ]
            ],
            [
                1.600000023841858,
                [
                    -0.024000102654099464,
                    -0.08805426210165024,
                    -0.019538037478923798,
                    0.9956348538398743
                ]
            ],
            [
                1.6666666269302368,
                [
                    -0.024049969390034676,
                    -0.0876583606004715,
                    -0.01960364729166031,
                    0.9956672787666321
                ]
            ],
            [
                1.7333333492279053,
                [
                    -0.023789651691913605,
                    -0.08730095624923706,
                    -0.019526807591319084,
                    0.9957064390182495
                ]
            ],
            [
                1.7999999523162842,
                [
                    -0.02333027310669422,
                    -0.08698448538780212,
                    -0.019303392618894577,
                    0.9957493543624878
                ]
            ],
            [
                1.8333333730697632,
                [
                    -0.02306114137172699,
                    -0.08684296160936356,
                    -0.01913529820740223,
                    0.9957712292671204
                ]
            ],
            [
                1.8666666746139526,
                [
                    -0.022784696891903877,
                    -0.08671350032091141,
                    -0.018928859382867813,
                    0.995792806148529
                ]
            ],
            [
                1.899999976158142,
                [
                    -0.022515276446938515,
                    -0.08659682422876358,
                    -0.018683377653360367,
                    0.9958137273788452
                ]
            ],
            [
                1.9333332777023315,
                [
                    -0.02226731739938259,
                    -0.08649369329214096,
                    -0.018398141488432884,
                    0.9958335757255554
                ]
            ],
            [
                1.9666666984558105,
                [
                    -0.022055337205529213,
                    -0.08640487492084503,
                    -0.01807239092886448,
                    0.995851993560791
                ]
            ],
            [
                2.0333333015441895,
                [
                    -0.021797606721520424,
                    -0.0862729549407959,
                    -0.017295951023697853,
                    0.9958828687667847
                ]
            ],
            [
                2.066666603088379,
                [
                    -0.021781079471111298,
                    -0.08623114973306656,
                    -0.01684342324733734,
                    0.9958946108818054
                ]
            ],
            [
                2.0999999046325684,
                [
                    -0.021858952939510345,
                    -0.08620613068342209,
                    -0.016346683725714684,
                    0.9959033727645874
                ]
            ],
            [
                2.133333444595337,
                [
                    -0.02203565277159214,
                    -0.08619751036167145,
                    -0.01580909453332424,
                    0.9959089756011963
                ]
            ],
            [
                2.200000047683716,
                [
                    -0.022684462368488312,
                    -0.08622659742832184,
                    -0.01463232934474945,
                    0.9959098696708679
                ]
            ],
            [
                2.2333333492279053,
                [
                    -0.023162303492426872,
                    -0.08626369386911392,
                    -0.0140005461871624,
                    0.9959047436714172
                ]
            ],
            [
                2.2666666507720947,
                [
                    -0.023745106533169746,
                    -0.08631528913974762,
                    -0.013345305807888508,
                    0.9958954453468323
                ]
            ],
            [
                2.299999952316284,
                [
                    -0.02443121001124382,
                    -0.08638074994087219,
                    -0.012672441080212593,
                    0.995881974697113
                ]
            ],
            [
                2.3333332538604736,
                [
                    -0.025216206908226013,
                    -0.08646068722009659,
                    -0.011989027261734009,
                    0.9958639144897461
                ]
            ],
            [
                2.366666555404663,
                [
                    -0.026090480387210846,
                    -0.08655551820993423,
                    -0.011304041370749474,
                    0.9958412051200867
                ]
            ],
            [
                2.4000000953674316,
                [
                    -0.027130024507641792,
                    -0.08664483577013016,
                    -0.010563368909060955,
                    0.99581378698349
                ]
            ],
            [
                2.433333396911621,
                [
                    -0.028411932289600372,
                    -0.0867077186703682,
                    -0.009725244715809822,
                    0.9957810640335083
                ]
            ],
            [
                2.4666666984558105,
                [
                    -0.02991667576134205,
                    -0.08674351871013641,
                    -0.008829259313642979,
                    0.9957422614097595
                ]
            ],
            [
                2.5,
                [
                    -0.03161969780921936,
                    -0.08675451576709747,
                    -0.007900379598140717,
                    0.995696485042572
                ]
            ],
            [
                2.5333333015441895,
                [
                    -0.033493783324956894,
                    -0.08674422651529312,
                    -0.006948370020836592,
                    0.9956431984901428
                ]
            ],
            [
                2.566666603088379,
                [
                    -0.035511694848537445,
                    -0.08671676367521286,
                    -0.005983070470392704,
                    0.9955819249153137
                ]
            ],
            [
                2.5999999046325684,
                [
                    -0.03764612227678299,
                    -0.08667661249637604,
                    -0.005014204420149326,
                    0.9955123066902161
                ]
            ],
            [
                2.633333444595337,
                [
                    -0.03986981511116028,
                    -0.08662844449281693,
                    -0.004051388707011938,
                    0.9954343438148499
                ]
            ],
            [
                2.6666667461395264,
                [
                    -0.04215526953339577,
                    -0.08657699078321457,
                    -0.003104237373918295,
                    0.9953480362892151
                ]
            ],
            [
                2.700000047683716,
                [
                    -0.0444752536714077,
                    -0.08652684092521667,
                    -0.0021822145208716393,
                    0.9952539801597595
                ]
            ],
            [
                2.7333333492279053,
                [
                    -0.0468023382127285,
                    -0.08648231625556946,
                    -0.0012947579380124807,
                    0.9951525926589966
                ]
            ],
            [
                2.7666666507720947,
                [
                    -0.049109138548374176,
                    -0.08644741773605347,
                    -0.00045116571709513664,
                    0.9950453042984009
                ]
            ],
            [
                2.799999952316284,
                [
                    -0.051368262618780136,
                    -0.08642563968896866,
                    0.0003392626531422138,
                    0.9949330687522888
                ]
            ],
            [
                2.8333332538604736,
                [
                    -0.053552355617284775,
                    -0.08641988039016724,
                    0.0010673420038074255,
                    0.994817852973938
                ]
            ],
            [
                2.866666555404663,
                [
                    -0.055634114891290665,
                    -0.08643243461847305,
                    0.0017238494474440813,
                    0.994701623916626
                ]
            ],
            [
                2.9000000953674316,
                [
                    -0.057586248964071274,
                    -0.08646482974290848,
                    0.002299654996022582,
                    0.9945865273475647
                ]
            ],
            [
                2.933333396911621,
                [
                    -0.05933871492743492,
                    -0.0865161120891571,
                    0.002770170569419861,
                    0.9944778680801392
                ]
            ],
            [
                2.9666666984558105,
                [
                    -0.06083562970161438,
                    -0.08658415824174881,
                    0.003116053529083729,
                    0.9943804740905762
                ]
            ],
            [
                3.0,
                [
                    -0.062070827931165695,
                    -0.08666802197694778,
                    0.003335957881063223,
                    0.9942960739135742
                ]
            ],
            [
                3.0333333015441895,
                [
                    -0.06303830444812775,
                    -0.08676645159721375,
                    0.003428463824093342,
                    0.994226336479187
                ]
            ],
            [
                3.066666603088379,
                [
                    -0.06370557844638824,
                    -0.08687839657068253,
                    0.003380502574145794,
                    0.9941741824150085
                ]
            ],
            [
                3.0999999046325684,
                [
                    -0.06405100226402283,
                    -0.08700218051671982,
                    0.0031837220303714275,
                    0.9941418170928955
                ]
            ],
            [
                3.133333444595337,
                [
                    -0.06408795714378357,
                    -0.08713477849960327,
                    0.002844340167939663,
                    0.994128942489624
                ]
            ],
            [
                3.1666667461395264,
                [
                    -0.06383831799030304,
                    -0.08727271109819412,
                    0.0023725712671875954,
                    0.9941340684890747
                ]
            ],
            [
                3.200000047683716,
                [
                    -0.06333983689546585,
                    -0.08741290867328644,
                    0.0017860567895695567,
                    0.9941548705101013
                ]
            ],
            [
                3.2333333492279053,
                [
                    -0.06260737031698227,
                    -0.08755015581846237,
                    0.0010951602598652244,
                    0.9941902756690979
                ]
            ],
            [
                3.2666666507720947,
                [
                    -0.061636462807655334,
                    -0.087677963078022,
                    0.00030875709489919245,
                    0.9942401051521301
                ]
            ],
            [
                3.299999952316284,
                [
                    -0.06044907867908478,
                    -0.08779249340295792,
                    -0.0005554441595450044,
                    0.9943028092384338
                ]
            ],
            [
                3.3333332538604736,
                [
                    -0.05906979739665985,
                    -0.08792241662740707,
                    -0.001629738020710647,
                    0.9943730235099792
                ]
            ],
            [
                3.366666555404663,
                [
                    -0.05752989649772644,
                    -0.08808953315019608,
                    -0.003005216596648097,
                    0.9944453239440918
                ]
            ],
            [
                3.4000000953674316,
                [
                    -0.05586659908294678,
                    -0.08825594931840897,
                    -0.004557458683848381,
                    0.9945195317268372
                ]
            ],
            [
                3.433333396911621,
                [
                    -0.05412176996469498,
                    -0.08839334547519684,
                    -0.006188693456351757,
                    0.9945949912071228
                ]
            ],
            [
                3.4666666984558105,
                [
                    -0.052328940480947495,
                    -0.08850640058517456,
                    -0.007867524400353432,
                    0.9946690201759338
                ]
            ],
            [
                3.5,
                [
                    -0.05052121356129646,
                    -0.08860114216804504,
                    -0.0095629021525383,
                    0.9947391748428345
                ]
            ],
            [
                3.5333333015441895,
                [
                    -0.048731546849012375,
                    -0.08868437260389328,
                    -0.011244231835007668,
                    0.9948035478591919
                ]
            ],
            [
                3.566666603088379,
                [
                    -0.04699234291911125,
                    -0.08876318484544754,
                    -0.012881310656666756,
                    0.9948602318763733
                ]
            ],
            [
                3.5999999046325684,
                [
                    -0.04532359540462494,
                    -0.08884371817111969,
                    -0.014448333531618118,
                    0.9949090480804443
                ]
            ],
            [
                3.633333444595337,
                [
                    -0.043757881969213486,
                    -0.0889325886964798,
                    -0.015915174037218094,
                    0.9949487447738647
                ]
            ],
            [
                3.6666667461395264,
                [
                    -0.04234618321061134,
                    -0.08903646469116211,
                    -0.017245201393961906,
                    0.9949783682823181
                ]
            ],
            [
                3.700000047683716,
                [
                    -0.041111405938863754,
                    -0.08915740251541138,
                    -0.018414011225104332,
                    0.9949983358383179
                ]
            ],
            [
                3.7333333492279053,
                [
                    -0.04006481543183327,
                    -0.08929332345724106,
                    -0.01940182037651539,
                    0.9950101971626282
                ]
            ],
            [
                3.7666666507720947,
                [
                    -0.039209384471178055,
                    -0.08943738788366318,
                    -0.020193081349134445,
                    0.9950155019760132
                ]
            ],
            [
                3.799999952316284,
                [
                    -0.038542088121175766,
                    -0.08957890421152115,
                    -0.020774560049176216,
                    0.995016872882843
                ]
            ],
            [
                3.8333332538604736,
                [
                    -0.03807170316576958,
                    -0.08970621228218079,
                    -0.021126653999090195,
                    0.9950160980224609
                ]
            ],
            [
                3.933333396911621,
                [
                    -0.037553660571575165,
                    -0.08984576165676117,
                    -0.02071549743413925,
                    0.9950318336486816
                ]
            ],
            [
                3.9666666984558105,
                [
                    -0.0375891849398613,
                    -0.08980244398117065,
                    -0.02022361010313034,
                    0.9950445294380188
                ]
            ],
            [
                4.0,
                [
                    -0.037688300013542175,
                    -0.08977430313825607,
                    -0.019840076565742493,
                    0.9950510263442993
                ]
            ],
            [
                4.066666603088379,
                [
                    -0.037997838109731674,
                    -0.08973832428455353,
                    -0.019136834889650345,
                    0.9950562715530396
                ]
            ],
            [
                4.099999904632568,
                [
                    -0.03817890211939812,
                    -0.0897194966673851,
                    -0.018741924315690994,
                    0.995058536529541
                ]
            ],
            [
                4.133333206176758,
                [
                    -0.03836670517921448,
                    -0.089698925614357,
                    -0.018327150493860245,
                    0.995060920715332
                ]
            ],
            [
                4.166666507720947,
                [
                    -0.03855342045426369,
                    -0.0896759107708931,
                    -0.017899245023727417,
                    0.9950635433197021
                ]
            ],
            [
                4.233333110809326,
                [
                    -0.038892827928066254,
                    -0.08962058275938034,
                    -0.01703060045838356,
                    0.9950705766677856
                ]
            ],
            [
                4.266666889190674,
                [
                    -0.039030615240335464,
                    -0.08958761394023895,
                    -0.016602925956249237,
                    0.9950754046440125
                ]
            ],
            [
                4.300000190734863,
                [
                    -0.039137423038482666,
                    -0.08955080807209015,
                    -0.016188213601708412,
                    0.9950813055038452
                ]
            ],
            [
                4.333333492279053,
                [
                    -0.03920614346861839,
                    -0.08951009809970856,
                    -0.01579270325601101,
                    0.9950886368751526
                ]
            ],
            [
                4.366666793823242,
                [
                    -0.03922976925969124,
                    -0.08946543186903,
                    -0.01542251743376255,
                    0.9950975179672241
                ]
            ],
            [
                4.400000095367432,
                [
                    -0.03920140862464905,
                    -0.08941678702831268,
                    -0.01508363988250494,
                    0.9951082468032837
                ]
            ],
            [
                4.4666666984558105,
                [
                    -0.03896113857626915,
                    -0.08930768072605133,
                    -0.01452324353158474,
                    0.9951357841491699
                ]
            ],
            [
                4.5,
                [
                    -0.038735531270504,
                    -0.08924717456102371,
                    -0.014313196763396263,
                    0.9951530694961548
                ]
            ],
            [
                4.5333333015441895,
                [
                    -0.03843036666512489,
                    -0.08918262273073196,
                    -0.014157460071146488,
                    0.995172917842865
                ]
            ],
            [
                4.599999904632568,
                [
                    -0.03754974156618118,
                    -0.08904029428958893,
                    -0.014032987877726555,
                    0.9952211380004883
                ]
            ],
            [
                4.633333206176758,
                [
                    -0.03695876896381378,
                    -0.0889616385102272,
                    -0.014076135121285915,
                    0.9952495694160461
                ]
            ],
            [
                4.666666507720947,
                [
                    -0.036244314163923264,
                    -0.0888764038681984,
                    -0.01420294027775526,
                    0.9952816963195801
                ]
            ],
            [
                4.699999809265137,
                [
                    -0.0353885143995285,
                    -0.08878318965435028,
                    -0.014423450455069542,
                    0.9953176379203796
                ]
            ],
            [
                4.733333110809326,
                [
                    -0.034392569214105606,
                    -0.08868163079023361,
                    -0.014739328995347023,
                    0.9953569769859314
                ]
            ],
            [
                4.766666889190674,
                [
                    -0.033259399235248566,
                    -0.08857134729623795,
                    -0.015151389874517918,
                    0.9953991174697876
                ]
            ],
            [
                4.800000190734863,
                [
                    -0.031993526965379715,
                    -0.0884522944688797,
                    -0.015660587698221207,
                    0.9954432845115662
                ]
            ],
            [
                4.833333492279053,
                [
                    -0.0306019876152277,
                    -0.0883244127035141,
                    -0.016267236322164536,
                    0.9954887628555298
                ]
            ],
            [
                4.866666793823242,
                [
                    -0.02908818982541561,
                    -0.08817342668771744,
                    -0.016956351697444916,
                    0.9955360293388367
                ]
            ],
            [
                4.900000095367432,
                [
                    -0.027445470914244652,
                    -0.0879848450422287,
                    -0.017705805599689484,
                    0.9955862164497375
                ]
            ],
            [
                4.933333396911621,
                [
                    -0.025659576058387756,
                    -0.08777736872434616,
                    -0.018474692478775978,
                    0.9956381916999817
                ]
            ],
            [
                4.9666666984558105,
                [
                    -0.023731447756290436,
                    -0.0875716283917427,
                    -0.01922955922782421,
                    0.9956898093223572
                ]
            ],
            [
                5.0,
                [
                    -0.021685414016246796,
                    -0.08737100660800934,
                    -0.019966449588537216,
                    0.9957396388053894
                ]
            ],
            [
                5.0333333015441895,
                [
                    -0.01954597607254982,
                    -0.08717898279428482,
                    -0.020681390538811684,
                    0.9957862496376038
                ]
            ],
            [
                5.066666603088379,
                [
                    -0.01733780838549137,
                    -0.08699910342693329,
                    -0.0213702991604805,
                    0.9958283305168152
                ]
            ],
            [
                5.099999904632568,
                [
                    -0.015085743740200996,
                    -0.08683482557535172,
                    -0.022028932347893715,
                    0.9958648681640625
                ]
            ],
            [
                5.133333206176758,
                [
                    -0.012814781628549099,
                    -0.08668945729732513,
                    -0.02265295386314392,
                    0.9958953857421875
                ]
            ],
            [
                5.166666507720947,
                [
                    -0.010550116188824177,
                    -0.08656612038612366,
                    -0.023237766698002815,
                    0.9959191679954529
                ]
            ],
            [
                5.199999809265137,
                [
                    -0.008317052386701107,
                    -0.08646757900714874,
                    -0.02377859503030777,
                    0.9959362149238586
                ]
            ],
            [
                5.233333110809326,
                [
                    -0.006141080521047115,
                    -0.08639626950025558,
                    -0.02427036128938198,
                    0.9959462285041809
                ]
            ],
            [
                5.266666889190674,
                [
                    -0.004047771450132132,
                    -0.08635426312685013,
                    -0.024707769975066185,
                    0.9959498643875122
                ]
            ],
            [
                5.300000190734863,
                [
                    -0.002062908373773098,
                    -0.08634313941001892,
                    -0.025085223838686943,
                    0.9959474802017212
                ]
            ],
            [
                5.333333492279053,
                [
                    -0.00021224016381893307,
                    -0.08636396378278732,
                    -0.025396857410669327,
                    0.9959398508071899
                ]
            ],
            [
                5.366666793823242,
                [
                    0.0014783910010010004,
                    -0.08641735464334488,
                    -0.025636551901698112,
                    0.9959280490875244
                ]
            ],
            [
                5.400000095367432,
                [
                    0.0029831225983798504,
                    -0.08650331944227219,
                    -0.02579791285097599,
                    0.995913028717041
                ]
            ],
            [
                5.433333396911621,
                [
                    0.004286172334104776,
                    -0.08661999553442001,
                    -0.025878718122839928,
                    0.99589604139328
                ]
            ],
            [
                5.4666666984558105,
                [
                    0.005378591828048229,
                    -0.08676400780677795,
                    -0.025879504159092903,
                    0.9958781599998474
                ]
            ],
            [
                5.5,
                [
                    0.006242914125323296,
                    -0.08693273365497589,
                    -0.025796888396143913,
                    0.9958605766296387
                ]
            ],
            [
                5.5333333015441895,
                [
                    0.006868894677609205,
                    -0.08712206035852432,
                    -0.025630490854382515,
                    0.9958441853523254
                ]
            ],
            [
                5.566666603088379,
                [
                    0.007242754567414522,
                    -0.08732784539461136,
                    -0.02537861280143261,
                    0.9958299398422241
                ]
            ],
            [
                5.599999904632568,
                [
                    0.00735536077991128,
                    -0.0875449925661087,
                    -0.025041600689291954,
                    0.9958186149597168
                ]
            ],
            [
                5.633333206176758,
                [
                    0.00720001757144928,
                    -0.0877695232629776,
                    -0.02462104894220829,
                    0.9958105683326721
                ]
            ],
            [
                5.666666507720947,
                [
                    0.006775335408747196,
                    -0.0879964828491211,
                    -0.024120504036545753,
                    0.9958056807518005
                ]
            ],
            [
                5.699999809265137,
                [
                    0.0060844458639621735,
                    -0.08819711208343506,
                    -0.02351621724665165,
                    0.9958068132400513
                ]
            ],
            [
                5.733333110809326,
                [
                    0.005135959014296532,
                    -0.08834507316350937,
                    -0.022799991071224213,
                    0.9958158135414124
                ]
            ],
            [
                5.766666889190674,
                [
                    0.003948059398680925,
                    -0.08843719214200974,
                    -0.02201121672987938,
                    0.9958307147026062
                ]
            ],
            [
                5.800000190734863,
                [
                    0.0025440803728997707,
                    -0.08847498148679733,
                    -0.02117486670613289,
                    0.995850145816803
                ]
            ],
            [
                5.833333492279053,
                [
                    0.000950007583014667,
                    -0.08846285194158554,
                    -0.020301315933465958,
                    0.9958721399307251
                ]
            ],
            [
                5.866666793823242,
                [
                    -0.0008081180858425796,
                    -0.08840607851743698,
                    -0.01940084993839264,
                    0.9958952069282532
                ]
            ],
            [
                5.900000095367432,
                [
                    -0.0027042042929679155,
                    -0.0883103609085083,
                    -0.018483715131878853,
                    0.9959178566932678
                ]
            ],
            [
                5.933333396911621,
                [
                    -0.004712124355137348,
                    -0.08818187564611435,
                    -0.01756005361676216,
                    0.9959384799003601
                ]
            ],
            [
                5.9666666984558105,
                [
                    -0.006805650424212217,
                    -0.08802689611911774,
                    -0.01663987897336483,
                    0.9959559440612793
                ]
            ],
            [
                6.0,
                [
                    -0.008958561345934868,
                    -0.0878518670797348,
                    -0.015733081847429276,
                    0.9959689974784851
                ]
            ],
            [
                6.0333333015441895,
                [
                    -0.011144571006298065,
                    -0.08766299486160278,
                    -0.014849364757537842,
                    0.9959771633148193
                ]
            ],
            [
                6.066666603088379,
                [
                    -0.013337363488972187,
                    -0.08746641874313354,
                    -0.013998359441757202,
                    0.995979905128479
                ]
            ],
            [
                6.099999904632568,
                [
                    -0.015510592609643936,
                    -0.08726778626441956,
                    -0.013189509510993958,
                    0.9959768056869507
                ]
            ],
            [
                6.133333206176758,
                [
                    -0.017637908458709717,
                    -0.08707240968942642,
                    -0.012432114221155643,
                    0.995968222618103
                ]
            ],
            [
                6.166666507720947,
                [
                    -0.01969292387366295,
                    -0.0868849977850914,
                    -0.011735420674085617,
                    0.9959545731544495
                ]
            ],
            [
                6.199999809265137,
                [
                    -0.021649321541190147,
                    -0.0867096483707428,
                    -0.011108523234724998,
                    0.9959365129470825
                ]
            ],
            [
                6.233333110809326,
                [
                    -0.023480691015720367,
                    -0.08654975146055222,
                    -0.01056052464991808,
                    0.9959148168563843
                ]
            ],
            [
                6.266666889190674,
                [
                    -0.025160769000649452,
                    -0.08640800416469574,
                    -0.010100302286446095,
                    0.9958908557891846
                ]
            ],
            [
                6.300000190734863,
                [
                    -0.026663197204470634,
                    -0.08628629893064499,
                    -0.009736881591379642,
                    0.9958659410476685
                ]
            ],
            [
                6.333333492279053,
                [
                    -0.027961786836385727,
                    -0.08618570864200592,
                    -0.009479069150984287,
                    0.9958416223526001
                ]
            ],
            [
                6.366666793823242,
                [
                    -0.029004177078604698,
                    -0.08610529452562332,
                    -0.009346972219645977,
                    0.9958199262619019
                ]
            ],
            [
                6.400000095367432,
                [
                    -0.029749099165201187,
                    -0.08604380488395691,
                    -0.009355928748846054,
                    0.99580317735672
                ]
            ],
            [
                6.4666666984558105,
                [
                    -0.03032774105668068,
                    -0.08597321808338165,
                    -0.009797083213925362,
                    0.9957875609397888
                ]
            ],
            [
                6.5,
                [
                    -0.030181370675563812,
                    -0.08596203476190567,
                    -0.010216042399406433,
                    0.9957887530326843
                ]
            ],
            [
                6.5333333015441895,
                [
                    -0.029773788526654243,
                    -0.08596611768007278,
                    -0.010751255787909031,
                    0.9957951307296753
                ]
            ],
            [
                6.566666603088379,
                [
                    -0.029125019907951355,
                    -0.08598420768976212,
                    -0.01138570997864008,
                    0.9958056211471558
                ]
            ],
            [
                6.599999904632568,
                [
                    -0.028262052685022354,
                    -0.0860166996717453,
                    -0.012101023457944393,
                    0.9958193302154541
                ]
            ],
            [
                6.633333206176758,
                [
                    -0.027214638888835907,
                    -0.08609757572412491,
                    -0.013027808628976345,
                    0.9958298206329346
                ]
            ]
        ]
    }
}
